prawdditions/__init__.py
prawdditions/const.py
prawdditions-0.1.2.dist-info/DESCRIPTION.rst
prawdditions-0.1.2.dist-info/METADATA
prawdditions-0.1.2.dist-info/RECORD
prawdditions-0.1.2.dist-info/WHEEL
prawdditions-0.1.2.dist-info/metadata.json
prawdditions-0.1.2.dist-info/top_level.txt
