Metadata-Version: 2.0
Name: prawdditions
Version: 0.1.2
Summary: DESCRIPTION.
Home-page: https://github.com/praw-dev/prawdditions
Author: Randall Goodman
Author-email: randy@kindofabigdeal.org
License: Simplified BSD License
Keywords: praw additions
Platform: UNKNOWN
Classifier: Development Status :: 4 - Beta
Classifier: Intended Audience :: Developers
Classifier: License :: OSI Approved :: BSD License
Classifier: Natural Language :: English
Classifier: Programming Language :: Python
Classifier: Programming Language :: Python :: 2.7
Classifier: Programming Language :: Python :: 3
Classifier: Programming Language :: Python :: 3.3
Classifier: Programming Language :: Python :: 3.4
Classifier: Programming Language :: Python :: 3.5
Classifier: Programming Language :: Python :: Implementation :: CPython
Requires-Dist: praw (<6.0,>=5.0.0)
